{
  "packageId": "au.com.banksiasprings.truecost",
  "host": "banksiasprings.github.io",
  "name": "TRUE COST",
  "launcherName": "TrueCost",
  "display": "standalone",
  "themeColor": "#2D5016",
  "navigationColor": "#2D5016",
  "navigationColorDark": "#1a3009",
  "backgroundColor": "#FAFAF8",
  "enableNotifications": false,
  "startUrl": "/truecost/",
  "iconUrl": "https://banksiasprings.github.io/truecost/assets/icons/icon-512.png",
  "maskableIconUrl": "https://banksiasprings.github.io/truecost/assets/icons/icon-512.png",
  "appVersion": "1",
  "appVersionName": "1.0.0",
  "signingKey": {
    "path": "android.keystore",
    "alias": "android"
  },
  "signingKeyFullName": "TrueCost App",
  "signingKeyOrganization": "Banksia Springs",
  "signingKeyOrganizationalUnit": "Development",
  "signingKeyCountry": "AU",
  "signingKeyPassword": "android",
  "keyStorePassword": "android",
  "minSdkVersion": 21,
  "targetSdkVersion": 34,
  "orientation": "portrait",
  "enableSiteSettingsShortcut": true,
  "isChromeOSOnly": false,
  "fullScopeUrl": "https://banksiasprings.github.io/truecost/",
  "webManifestUrl": "https://banksiasprings.github.io/truecost/manifest.json",
  "fallbackType": "customtabs",
  "features": {},
  "shortcuts": [],
  "splashScreenFadeOutDuration": 300
}